AGENT_INTEGRATION.md
LICENSE
README.md
ROADMAP.md
paperpipe/__init__.py
paperpipe/__main__.py
paperpipe/cli.py.backup
paperpipe/config.py
paperpipe/core.py
paperpipe/install.py
paperpipe/leann.py
paperpipe/output.py
paperpipe/paper.py
paperpipe/paperqa.py
paperpipe/paperqa_mcp_server.py
paperpipe/search.py
paperpipe/cli/__init__.py
paperpipe/cli/ask.py
paperpipe/cli/export.py
paperpipe/cli/helpers.py
paperpipe/cli/index.py
paperpipe/cli/models.py
paperpipe/cli/papers.py
paperpipe/cli/rebuild.py
paperpipe/cli/search_cli.py
paperpipe/cli/system.py
prompts/claude/compare-papers.md
prompts/claude/curate-paper-note.md
prompts/claude/ground-with-paper.md
prompts/claude/papi-init.md
prompts/claude/papi.md
prompts/claude/verify-with-paper.md
prompts/codex/compare-papers.md
prompts/codex/curate-paper-note.md
prompts/codex/ground-with-paper.md
prompts/codex/papi-init.md
prompts/codex/papi.md
prompts/codex/verify-with-paper.md
prompts/gemini/compare-papers.toml
prompts/gemini/curate-paper-note.toml
prompts/gemini/ground-with-paper.toml
prompts/gemini/papi-init.toml
prompts/gemini/papi-list.toml
prompts/gemini/papi-path.toml
prompts/gemini/papi-run.toml
prompts/gemini/papi-search.toml
prompts/gemini/papi-show-eq.toml
prompts/gemini/papi-show-summary.toml
prompts/gemini/papi-show-tex.toml
prompts/gemini/papi-tags.toml
prompts/gemini/papi.toml
prompts/gemini/verify-with-paper.toml
skill/SKILL.md
skill/commands.md
paperpipe-1.3.0.dist-info/METADATA
paperpipe-1.3.0.dist-info/WHEEL
paperpipe-1.3.0.dist-info/entry_points.txt
paperpipe-1.3.0.dist-info/licenses/LICENSE
paperpipe-1.3.0.dist-info/RECORD
