Metadata-Version: 2.4
Name: paperpipe
Version: 1.3.0
Summary: Unified paper database for coding agents + PaperQA2
Project-URL: Homepage, https://github.com/hummat/paperpipe
Project-URL: Documentation, https://github.com/hummat/paperpipe#readme
Project-URL: Repository, https://github.com/hummat/paperpipe
Author: Matthias Humt
License: MIT License
License-File: LICENSE
Keywords: arxiv,coding-agent,llm,paperqa,papers,research
Classifier: Development Status :: 3 - Alpha
Classifier: Intended Audience :: Developers
Classifier: Intended Audience :: Science/Research
Classifier: License :: OSI Approved :: MIT License
Classifier: Programming Language :: Python :: 3
Classifier: Programming Language :: Python :: 3.10
Classifier: Programming Language :: Python :: 3.11
Classifier: Programming Language :: Python :: 3.12
Requires-Python: >=3.10
Requires-Dist: arxiv>=2.0.0
Requires-Dist: click>=8.0.0
Requires-Dist: requests>=2.28.0
Requires-Dist: tomli>=2.0.0; python_version < '3.11'
Provides-Extra: all
Requires-Dist: bibtexparser>=1.4.0; extra == 'all'
Requires-Dist: leann-backend-hnsw>=0.3.5; extra == 'all'
Requires-Dist: leann-core>=0.3.5; extra == 'all'
Requires-Dist: litellm>=1.0.0; extra == 'all'
Requires-Dist: mcp>=1.0.0; (python_version >= '3.11') and extra == 'all'
Requires-Dist: paper-qa>=5.0.0; (python_version >= '3.11') and extra == 'all'
Requires-Dist: paper-qa[docling,image,ldp,local,memory,nemotron,office,openreview,pymupdf,pypdf-enhanced,pypdf-media,qdrant,zotero]>=5.0.0; (python_version >= '3.11') and extra == 'all'
Requires-Dist: pymupdf4llm; extra == 'all'
Requires-Dist: pymupdf>=1.24.0; extra == 'all'
Provides-Extra: bibtex
Requires-Dist: bibtexparser>=1.4.0; extra == 'bibtex'
Provides-Extra: dev
Requires-Dist: build>=1.0.0; extra == 'dev'
Requires-Dist: pyright>=1.1.385; extra == 'dev'
Requires-Dist: pytest-cov>=7.0.0; extra == 'dev'
Requires-Dist: ruff>=0.1.0; extra == 'dev'
Requires-Dist: twine>=5.0.0; extra == 'dev'
Provides-Extra: figures
Requires-Dist: pymupdf>=1.24.0; extra == 'figures'
Provides-Extra: leann
Requires-Dist: leann-backend-hnsw>=0.3.5; extra == 'leann'
Requires-Dist: leann-core>=0.3.5; extra == 'leann'
Provides-Extra: llm
Requires-Dist: litellm>=1.0.0; extra == 'llm'
Provides-Extra: mcp
Requires-Dist: mcp>=1.0.0; (python_version >= '3.11') and extra == 'mcp'
Requires-Dist: paper-qa>=5.0.0; (python_version >= '3.11') and extra == 'mcp'
Provides-Extra: paperqa
Requires-Dist: paper-qa[docling,image,ldp,local,memory,nemotron,office,openreview,pymupdf,pypdf-enhanced,pypdf-media,qdrant,zotero]>=5.0.0; (python_version >= '3.11') and extra == 'paperqa'
Requires-Dist: pymupdf4llm; extra == 'paperqa'
